chardiff_html/__init__.py
chardiff_html/chardiff_html.py
chardiff_html-0.1.1.dist-info/LICENSE
chardiff_html-0.1.1.dist-info/WHEEL
chardiff_html-0.1.1.dist-info/METADATA
chardiff_html-0.1.1.dist-info/RECORD
