Metadata-Version: 2.1
Name: chardiff-html
Version: 0.1.1
Summary: 
Home-page: https://github.com/tyo-yo/chardiff_html
License: MIT
Author: Tomoaki Nakamura
Author-email: tyo_yo@icloud.com
Requires-Python: >=3.7,<4.0
Classifier: License :: OSI Approved :: MIT License
Classifier: Programming Language :: Python :: 3
Classifier: Programming Language :: Python :: 3.7
Classifier: Programming Language :: Python :: 3.8
Project-URL: Repository, https://github.com/tyo-yo/chardiff_html
